hubble/__init__.py
hubble/client.py
hubble/consumer.py
hubble/request.py
hubble/utils.py
hubble/version.py
hubble_client-0.1.dist-info/LICENSE.md
hubble_client-0.1.dist-info/METADATA
hubble_client-0.1.dist-info/WHEEL
hubble_client-0.1.dist-info/top_level.txt
hubble_client-0.1.dist-info/RECORD
